sigint_printstack/__init__.py
sigint_printstack-0.0.1.dist-info/DESCRIPTION.rst
sigint_printstack-0.0.1.dist-info/METADATA
sigint_printstack-0.0.1.dist-info/RECORD
sigint_printstack-0.0.1.dist-info/WHEEL
sigint_printstack-0.0.1.dist-info/metadata.json
sigint_printstack-0.0.1.dist-info/pbr.json
sigint_printstack-0.0.1.dist-info/top_level.txt
